odoo9_addon_auth_signup_verify_email-9.0.1.0.0.99.dev11-py2.7-nspkg.pth
odoo9_addon_auth_signup_verify_email-9.0.1.0.0.99.dev11.dist-info/DESCRIPTION.rst
odoo9_addon_auth_signup_verify_email-9.0.1.0.0.99.dev11.dist-info/METADATA
odoo9_addon_auth_signup_verify_email-9.0.1.0.0.99.dev11.dist-info/RECORD
odoo9_addon_auth_signup_verify_email-9.0.1.0.0.99.dev11.dist-info/WHEEL
odoo9_addon_auth_signup_verify_email-9.0.1.0.0.99.dev11.dist-info/metadata.json
odoo9_addon_auth_signup_verify_email-9.0.1.0.0.99.dev11.dist-info/namespace_packages.txt
odoo9_addon_auth_signup_verify_email-9.0.1.0.0.99.dev11.dist-info/top_level.txt
odoo_addons/auth_signup_verify_email/README.rst
odoo_addons/auth_signup_verify_email/__init__.py
odoo_addons/auth_signup_verify_email/__openerp__.py
odoo_addons/auth_signup_verify_email/controllers/__init__.py
odoo_addons/auth_signup_verify_email/controllers/main.py
odoo_addons/auth_signup_verify_email/i18n/auth_signup_verify_email.pot
odoo_addons/auth_signup_verify_email/i18n/ca.po
odoo_addons/auth_signup_verify_email/i18n/de.po
odoo_addons/auth_signup_verify_email/i18n/es.po
odoo_addons/auth_signup_verify_email/i18n/es_ES.po
odoo_addons/auth_signup_verify_email/i18n/hr_HR.po
odoo_addons/auth_signup_verify_email/i18n/it.po
odoo_addons/auth_signup_verify_email/i18n/pt_BR.po
odoo_addons/auth_signup_verify_email/i18n/sl.po
odoo_addons/auth_signup_verify_email/i18n/tr.po
odoo_addons/auth_signup_verify_email/static/description/icon.png
odoo_addons/auth_signup_verify_email/static/description/icon.svg
odoo_addons/auth_signup_verify_email/tests/__init__.py
odoo_addons/auth_signup_verify_email/tests/test_verify_email.py
odoo_addons/auth_signup_verify_email/views/signup.xml
