Metadata-Version: 2.0
Name: odoo9-addon-auth-signup-verify-email
Version: 9.0.1.0.0.99.dev11
Summary: Force uninvited users to use a good email for signup
Home-page: http://www.tecnativa.com
Author: Antiun Ingeniería S.L., Tecnativa, Odoo Community Association (OCA)
Author-email: support@odoo-community.org
License: AGPL-3
Platform: UNKNOWN
Classifier: Programming Language :: Python
Classifier: Framework :: Odoo
Classifier: License :: OSI Approved :: GNU Affero General Public License v3
Requires-Python: ~=2.7
Requires-Dist: lxml
Requires-Dist: odoo (<9.1a,>=9.0a)
Requires-Dist: validate-email
